{"name":"jfeedly","tagline":"Java wrapper for the Feedly API","body":"jfeedly\r\n-------\r\n\r\nJava wrapper for the Feedly API\r\n\r\nHow to use jfeedly\r\n==================\r\n\r\n[Look at this file](https://github.com/Kasoki/jfeedly/blob/master/src/de/kasoki/jfeedly/Example.java)\r\n\r\nUsed libraries\r\n==============\r\n\r\n* JSON implementation of [json.org](http://json.org)\r\n\r\n\r\nLicence\r\n=======\r\n\r\njfeedly is licenced under the terms of the Apache Licence v2.","google":"","note":"Don't delete this file! It's used internally to help with page regeneration."}